pyquante2/__init__.py
pyquante2/cbecke.cpython-313-darwin.so
pyquante2/constants.py
pyquante2/orbman.py
pyquante2/settings.py
pyquante2/utils.py
pyquante2/basis/__init__.py
pyquante2/basis/basisset.py
pyquante2/basis/cgbf.py
pyquante2/basis/data.py
pyquante2/basis/pgbf.py
pyquante2/basis/tools.py
pyquante2/cints/cbecke.c
pyquante2/cints/chgp.c
pyquante2/cints/chgp.h
pyquante2/cints/chgp_wrap.c
pyquante2/cints/cints.c
pyquante2/cints/cints.h
pyquante2/cints/cone_wrap.c
pyquante2/cints/crys.c
pyquante2/cints/crys.h
pyquante2/cints/crys_wrap.c
pyquante2/cints/ctwo_wrap.c
pyquante2/cints/hgp.cpython-313-darwin.so
pyquante2/cints/one.cpython-313-darwin.so
pyquante2/cints/rys.cpython-313-darwin.so
pyquante2/cints/two.cpython-313-darwin.so
pyquante2/dft/__init__.py
pyquante2/dft/dft.py
pyquante2/dft/functionals.py
pyquante2/dft/reference.py
pyquante2/geo/__init__.py
pyquante2/geo/atom.py
pyquante2/geo/elements.py
pyquante2/geo/molecule.py
pyquante2/geo/samples.py
pyquante2/geo/zmatrix.py
pyquante2/graphics/__init__.py
pyquante2/graphics/contourplot.py
pyquante2/graphics/lineplot.py
pyquante2/graphics/maya.py
pyquante2/graphics/vtkplot.py
pyquante2/grid/__init__.py
pyquante2/grid/atomic_grid.py
pyquante2/grid/becke.py
pyquante2/grid/data.py
pyquante2/grid/grid.py
pyquante2/grid/lebedev.py
pyquante2/grid/legendre.py
pyquante2/hylleraas/helios.py
pyquante2/hylleraas/helios_supplemental.py
pyquante2/ints/__init__.py
pyquante2/ints/hgp.py
pyquante2/ints/hgp_shell.py
pyquante2/ints/integrals.py
pyquante2/ints/one.py
pyquante2/ints/rys.py
pyquante2/ints/two.py
pyquante2/io/cml.py
pyquante2/pt/__init__.py
pyquante2/pt/mp2.py
pyquante2/scf/__init__.py
pyquante2/scf/hamiltonians.py
pyquante2/scf/iterators.py
pyquante2/scf/mcscf.py
pyquante2/viewer/__init__.py
pyquante2/viewer/nwviewer.py
pyquante2/viewer/trackball_camera.py
pyquante2/viewer/viewer.py
pyquante2-0.2.0.dist-info/licenses/LICENSE
pyquante2-0.2.0.dist-info/METADATA
pyquante2-0.2.0.dist-info/WHEEL
pyquante2-0.2.0.dist-info/top_level.txt
pyquante2-0.2.0.dist-info/RECORD
