Metadata-Version: 2.4
Name: pyquante2
Version: 0.2.0
Summary: Python quantum chemistry routines
Author-email: Rick Muller <rpmuller@gmail.com>
License: BSD-3-Clause
Project-URL: Homepage, https://github.com/rpmuller/pyquante2
Project-URL: Repository, https://github.com/rpmuller/pyquante2
Project-URL: Bug Tracker, https://github.com/rpmuller/pyquante2/issues
Keywords: quantum-chemistry,chemistry,computational-chemistry,hartree-fock,dft,molecular-orbital
Classifier: Development Status :: 3 - Alpha
Classifier: Intended Audience :: Science/Research
Classifier: License :: OSI Approved :: BSD License
Classifier: Operating System :: OS Independent
Classifier: Programming Language :: Python :: 3
Classifier: Programming Language :: Python :: 3.11
Classifier: Programming Language :: Python :: 3.12
Classifier: Programming Language :: C
Classifier: Topic :: Scientific/Engineering :: Chemistry
Classifier: Topic :: Scientific/Engineering :: Physics
Requires-Python: >=3.11
License-File: LICENSE
Requires-Dist: numpy>=1.20
Provides-Extra: jupyter
Requires-Dist: ipykernel>=7.1.0; extra == "jupyter"
Provides-Extra: dev
Requires-Dist: pytest; extra == "dev"
Requires-Dist: matplotlib; extra == "dev"
Requires-Dist: build; extra == "dev"
Requires-Dist: ipykernel; extra == "dev"
Requires-Dist: twine; extra == "dev"
Provides-Extra: test
Requires-Dist: pytest; extra == "test"
Requires-Dist: matplotlib; extra == "test"
Requires-Dist: build; extra == "test"
Dynamic: license-file
